{"n_unenrolled": 4367, "victory_district": 6, "p_unenrolled": 65.56072662, "r_deviance_sigma": 0.42781121, "image_link": null, "delta_local_aid_percentage": -30.54086505, "state_senator": "Stephen M. Brewer ( D )", "total_votes": 3394, "region_office_address": "TBD", "py/object": "__main__.Town", "established": 1762, "votes": {"Patrick": 1350, "Baker": 1583, "Total": 3394, "Stein": 68, "Cahill": 393}, "n_green": 16, "d_deviance": 4.034246139, "n_republican": 799, "region_office": "Leominster", "p_baker": 46.64113141, "coordinates": [-72.15449891098248, 42.62389767764177], "registered_voters": {"Unenrolled": 4367, "Green-Rainbow": 16, "Republican": 799, "Democrat": 1438, "Total": 6661}, "elected_officials": {}, "local_aid_2013": 2239276.0, "state_rep": "Denise Andrews (D)", "SCM_email": "wgillmeister@charter.net", "papers": {"Athol Daily News": "http://atholdailynews.com/index.asp"}, "local_aid_2015": 2355775.0, "p_patrick": 39.77607543, "media_market": "", "leader": "Mayor: N/A", "delta_local_aid_per_capita": -75.04310268, "SCW_email": "jgaron98@aol.com", "staffer_phone": "(774) 573-3439", "p_participation": 50.9533103137667, "unemployment_difference_from_MA_average": 2.1, "SCM_name": "William Gillmeister", "unemployment_total": 397, "vote_percentages": {"% Patrick": 39.77607543, "% Cahill": 11.57925751, "% Baker": 46.64113141, "% Stein": 2.003535651}, "p_democrat": 21.5883501, "registered_percentages": {"% Green-Rainbow": 0.240204174, "% Democrat": 21.5883501, "% Republican": 11.99519592, "% Unenrolled": 65.56072662}, "percent_registered_republicans": 11.99519592, "r_deviance": 26.78179789, "percent_registered_unenrolled": 65.56072662, "federal_reps": "James McGovern (D)", "population": 11584, "SCW_phone": "508-347-4972", "slug": "athol", "p_green": 0.240204174, "region_staffer": "Ryan Chamberland", "name": "ATHOL", "gov_type": "open town meeting", "d_deviance_sigma": 0.17156678, "p_republican": 11.99519592, "staffer_email": "chamberland@massvictory.com", "delta_local_aid": -869299.3015, "county": "Worcester", "n_democrat": 1438, "SCW_name": "Janet Garon", "unemployment_percentage": 7.7, "local_aid_2008": 3108575.301, "region": "6", "SCM_phone": "508-867-9680"}