{"n_unenrolled": 6475, "victory_district": 5, "p_unenrolled": 59.9814729, "r_deviance_sigma": 0.955772549, "image_link": null, "delta_local_aid_percentage": -41.25269048, "state_senator": "Richard T. Moore ( D )", "total_votes": 6376, "region_office_address": "197 Main Street Suite 203", "py/object": "__main__.Town", "established": 1719, "votes": {"Patrick": 2191, "Baker": 3355, "Total": 6376, "Stein": 75, "Cahill": 755}, "n_green": 8, "d_deviance": -7.695810575, "n_republican": 1426, "region_office": "Milford Office", "p_baker": 52.61919699, "coordinates": [-71.44142044752762, 42.13481573168869], "registered_voters": {"Unenrolled": 6475, "Green-Rainbow": 8, "Republican": 1426, "Democrat": 2838, "Total": 10795}, "elected_officials": {}, "local_aid_2013": 1435208.0, "state_rep": "Kevin Kuros (R)", "SCM_email": "mikepotaski@hotmail.com", "papers": {"Country Gazette": "http://bellingham.wickedlocal.com/"}, "local_aid_2015": 1509875.0, "p_patrick": 34.36323714, "media_market": "Boston", "leader": "Mayor: N/A", "delta_local_aid_per_capita": -53.34256788, "SCW_email": "kimberlyroy11@yahoo.com", "staffer_phone": "(774) 573-3439", "p_participation": 59.06438165817508, "unemployment_difference_from_MA_average": 0.5, "SCM_name": "Mike Potaski", "unemployment_total": 594, "vote_percentages": {"% Patrick": 34.36323714, "% Cahill": 11.8412798, "% Baker": 52.61919699, "% Stein": 1.176286073}, "p_democrat": 26.28994905, "registered_percentages": {"% Green-Rainbow": 0.074108384, "% Democrat": 26.28994905, "% Republican": 13.20981936, "% Unenrolled": 59.9814729}, "percent_registered_republicans": 13.20981936, "r_deviance": 31.48593341, "percent_registered_unenrolled": 59.9814729, "federal_reps": "Joseph Kennedy III (D); James McGovern (D)", "population": 16332, "SCW_phone": "508-266-0904", "slug": "bellingham", "p_green": 0.074108384, "region_staffer": "Ryan Chamberland", "name": "BELLINGHAM", "gov_type": "open town meeting", "d_deviance_sigma": -0.995603042, "p_republican": 13.20981936, "staffer_email": "chamberland@massvictory.com", "delta_local_aid": -871190.8187, "county": "Norfolk", "n_democrat": 2838, "SCW_name": "Kimberly Roy", "unemployment_percentage": 6.1, "local_aid_2008": 2306398.819, "region": "6", "SCM_phone": "508-234-5852"}