{"n_unenrolled": 27551, "victory_district": 4, "p_unenrolled": 50.38311724, "r_deviance_sigma": 0.487293057, "image_link": null, "delta_local_aid_percentage": -41.25268141, "state_senator": "Eileen M. Donoghue ( D )", "total_votes": 22078, "region_office_address": "227 Chelmsford Street", "py/object": "__main__.Town", "established": 1826, "votes": {"Patrick": 10792, "Baker": 8954, "Total": 22078, "Stein": 324, "Cahill": 2008}, "n_green": 78, "d_deviance": -11.41721236, "n_republican": 4816, "region_office": "Chelmsford Office", "p_baker": 40.5562098, "coordinates": [-71.36898549162272, 42.66170360656441], "registered_voters": {"Unenrolled": 27551, "Green-Rainbow": 78, "Republican": 4816, "Democrat": 21926, "Total": 54683}, "elected_officials": {}, "local_aid_2013": 21304471.0, "state_rep": "Thomas A. Golden, Jr. (D)", "SCM_email": "rick@1aauto.com", "papers": {"Lowell Sun": "http://www.lowellsun.com/"}, "local_aid_2015": 22412842.0, "p_patrick": 48.88123924, "media_market": "Boston", "leader": "Mayor: Rodney Elliott", "delta_local_aid_per_capita": -121.406507, "SCW_email": "susan.slade1@verizon.net", "staffer_phone": "(774) 364-2035", "p_participation": 40.37452224640199, "unemployment_difference_from_MA_average": 1.1, "SCM_name": "Richard Green", "unemployment_total": 3428, "vote_percentages": {"% Patrick": 48.88123924, "% Cahill": 9.095026723, "% Baker": 40.5562098, "% Stein": 1.467524232}, "p_democrat": 40.09655652, "registered_percentages": {"% Green-Rainbow": 0.142640309, "% Democrat": 40.09655652, "% Republican": 8.807124701, "% Unenrolled": 50.38311724}, "percent_registered_republicans": 8.807124701, "r_deviance": 27.31178114, "percent_registered_unenrolled": 50.38311724, "federal_reps": "Niki Tsongas (D)", "population": 106519, "SCW_phone": "978-448-9391", "slug": "lowell", "p_green": 0.142640309, "region_staffer": "Chris Lane", "name": "LOWELL", "gov_type": "mayor-manager-council", "d_deviance_sigma": -1.365891777, "p_republican": 8.807124701, "staffer_email": "Chris@massvictory.com", "delta_local_aid": -12932099.72, "county": "Middlesex", "n_democrat": 21926, "SCW_name": "Susan Slade", "unemployment_percentage": 6.7, "local_aid_2008": 34236570.72, "region": "4", "SCM_phone": "978-433-4115"}