{"n_unenrolled": 1864, "victory_district": 3, "p_unenrolled": 53.51708297, "r_deviance_sigma": -0.638726001, "image_link": null, "delta_local_aid_percentage": -41.25200576, "state_senator": "Daniel A. Wolf ( D )", "total_votes": 2109, "region_office_address": "124 Long Pong Road, Suite 3", "py/object": "__main__.Town", "established": 1880, "votes": {"Patrick": 1205, "Baker": 713, "Total": 2109, "Stein": 31, "Cahill": 160}, "n_green": 6, "d_deviance": 3.186927682, "n_republican": 375, "region_office": "Plymouth Office", "p_baker": 33.8074917, "coordinates": [-70.55890184901763, 41.46246859305824], "registered_voters": {"Unenrolled": 1864, "Green-Rainbow": 6, "Republican": 375, "Democrat": 1224, "Total": 3483}, "elected_officials": {}, "local_aid_2013": 61514.0, "state_rep": "Timothy R. Madden (D)", "SCM_email": "manzellif@comcast.net", "papers": {}, "local_aid_2015": 64714.0, "p_patrick": 57.13608345, "media_market": "Boston", "leader": "Mayor: N/A", "delta_local_aid_per_capita": -8.248031919, "SCW_email": "electjudycrocker@gmail.com", "staffer_phone": "(919) 428-6528", "p_participation": 60.55124892334195, "unemployment_difference_from_MA_average": 1.6, "SCM_name": "Francis Manzelli", "unemployment_total": 195, "vote_percentages": {"% Patrick": 57.13608345, "% Cahill": 7.586533902, "% Baker": 33.8074917, "% Stein": 1.469890944}, "p_democrat": 35.14211886, "registered_percentages": {"% Green-Rainbow": 0.172265289, "% Democrat": 35.14211886, "% Republican": 10.76658053, "% Unenrolled": 53.51708297}, "percent_registered_republicans": 10.76658053, "r_deviance": 17.27895133, "percent_registered_unenrolled": 53.51708297, "federal_reps": "William Keating (D)", "population": 4527, "SCW_phone": "508-737-1107", "slug": "oak_bluffs", "p_green": 0.172265289, "region_staffer": "Ben Keilman", "name": "OAK BLUFFS", "gov_type": "open town meeting", "d_deviance_sigma": 0.087256486, "p_republican": 10.76658053, "staffer_email": "ben@massvictory.com", "delta_local_aid": -37338.8405, "county": "Dukes", "n_democrat": 1224, "SCW_name": "Judy Crocker", "unemployment_percentage": 7.2, "local_aid_2008": 98852.8405, "region": "3", "SCM_phone": "508-965-7643"}