{"n_unenrolled": 217, "victory_district": 7, "p_unenrolled": 59.1280654, "r_deviance_sigma": -0.324071264, "image_link": null, "delta_local_aid_percentage": -34.73798831, "state_senator": "Donald F. Humason, Jr. ( R )", "total_votes": 209, "region_office_address": "145 Shaker Road", "py/object": "__main__.Town", "established": 1810, "votes": {"Patrick": 70, "Baker": 119, "Total": 209, "Stein": 9, "Cahill": 11}, "n_green": 0, "d_deviance": 5.309378148, "n_republican": 85, "region_office": "East Longmeadow Office", "p_baker": 56.93779904, "coordinates": [-73.03483210707655, 42.14367513374284], "registered_voters": {"Unenrolled": 217, "Green-Rainbow": 0, "Republican": 85, "Democrat": 65, "Total": 367}, "elected_officials": {}, "local_aid_2013": 15633.0, "state_rep": "William Smitty Pignatelli (D)", "SCM_email": "berrena@juno.com", "papers": {}, "local_aid_2015": 16447.0, "p_patrick": 33.49282297, "media_market": "Springfield", "leader": "Mayor: N/A", "delta_local_aid_per_capita": -15.03474459, "SCW_email": "lindavac@aol.com", "staffer_phone": "(774) 573-3439", "p_participation": 56.94822888283378, "unemployment_difference_from_MA_average": -1.1, "SCM_name": "Richard Berrena", "unemployment_total": 12, "vote_percentages": {"% Patrick": 33.49282297, "% Cahill": 5.263157895, "% Baker": 56.93779904, "% Stein": 4.306220096}, "p_democrat": 17.71117166, "registered_percentages": {"% Green-Rainbow": 0.0, "% Democrat": 17.71117166, "% Republican": 23.16076294, "% Unenrolled": 59.1280654}, "percent_registered_republicans": 23.16076294, "r_deviance": 20.08252504, "percent_registered_unenrolled": 59.1280654, "federal_reps": "Richard Neal (D)", "population": 485, "SCW_phone": "413-210-6085", "slug": "tolland", "p_green": 0.0, "region_staffer": "Ryan Chamberland", "name": "TOLLAND", "gov_type": "open town meeting", "d_deviance_sigma": 0.298445587, "p_republican": 23.16076294, "staffer_email": "chamberland@massvictory.com", "delta_local_aid": -7291.851126, "county": "Hampden", "n_democrat": 65, "SCW_name": "Linda Vacon", "unemployment_percentage": 4.5, "local_aid_2008": 22924.85113, "region": "7", "SCM_phone": "413-534-0311"}