{"n_unenrolled": 10105, "victory_district": 4, "p_unenrolled": 62.70555383, "r_deviance_sigma": 0.75251214, "image_link": null, "delta_local_aid_percentage": -41.25267402, "state_senator": "Eileen M. Donoghue ( D )", "total_votes": 9703, "region_office_address": "227 Chelmsford Street", "py/object": "__main__.Town", "established": 1729, "votes": {"Patrick": 3832, "Baker": 5209, "Total": 9703, "Stein": 107, "Cahill": 555}, "n_green": 9, "d_deviance": 3.478623826, "n_republican": 2378, "region_office": "Chelmsford Office", "p_baker": 53.6844275, "coordinates": [-71.41764152776015, 42.65376486054291], "registered_voters": {"Unenrolled": 10105, "Green-Rainbow": 9, "Republican": 2378, "Democrat": 3567, "Total": 16115}, "elected_officials": {}, "local_aid_2013": 1797543.0, "state_rep": "James Arciero (D)", "SCM_email": "rick@1aauto.com", "papers": {"Westford Eagle": "http://westford.wickedlocal.com/"}, "local_aid_2015": 1891061.0, "p_patrick": 39.49294033, "media_market": "Boston", "leader": "Mayor: N/A", "delta_local_aid_per_capita": -49.70763987, "SCW_email": "susan.slade1@verizon.net", "staffer_phone": "(774) 364-2035", "p_participation": 60.21098355569345, "unemployment_difference_from_MA_average": -1.4, "SCM_name": "Richard Green", "unemployment_total": 516, "vote_percentages": {"% Patrick": 39.49294033, "% Cahill": 5.719880449, "% Baker": 53.6844275, "% Stein": 1.102751726}, "p_democrat": 22.13465715, "registered_percentages": {"% Green-Rainbow": 0.055848588, "% Democrat": 22.13465715, "% Republican": 14.7564381, "% Unenrolled": 62.70555383}, "percent_registered_republicans": 14.7564381, "r_deviance": 29.67488316, "percent_registered_unenrolled": 62.70555383, "federal_reps": "Niki Tsongas (D)", "population": 21951, "SCW_phone": "978-448-9394", "slug": "westford", "p_green": 0.055848588, "region_staffer": "Chris Lane", "name": "WESTFORD", "gov_type": "open town meeting", "d_deviance_sigma": 0.116280978, "p_republican": 14.7564381, "staffer_email": "Chris@massvictory.com", "delta_local_aid": -1091132.403, "county": "Middlesex", "n_democrat": 3567, "SCW_name": "Susan Slade", "unemployment_percentage": 4.2, "local_aid_2008": 2888675.403, "region": "4", "SCM_phone": "978-433-4118"}